src/__init__.py
src/utils/__init__.py
src/utils/etl_book_data.py
src/utils/goodreads_api.py
src/utils/goodreads_api_client/__init__.py
src/utils/goodreads_api_client/client.py
src/utils/goodreads_api_client/exceptions.py
src/utils/goodreads_api_client/transport.py
src/utils/goodreads_api_client/resources/__init__.py
src/utils/goodreads_api_client/resources/author.py
src/utils/goodreads_api_client/resources/author_following.py
src/utils/goodreads_api_client/resources/base.py
src/utils/goodreads_api_client/resources/book.py
src/utils/goodreads_api_client/resources/comment.py
src/utils/goodreads_api_client/resources/event.py
src/utils/goodreads_api_client/resources/follower.py
src/utils/goodreads_api_client/resources/friend.py
src/utils/goodreads_api_client/resources/group.py
src/utils/goodreads_api_client/resources/list.py
src/utils/goodreads_api_client/resources/notification.py
src/utils/goodreads_api_client/resources/owned_book.py
src/utils/goodreads_api_client/resources/quote.py
src/utils/goodreads_api_client/resources/rating.py
src/utils/goodreads_api_client/resources/read_status.py
src/utils/goodreads_api_client/resources/recommendation.py
src/utils/goodreads_api_client/resources/review.py
src/utils/goodreads_api_client/resources/series.py
src/utils/goodreads_api_client/resources/shelf.py
src/utils/goodreads_api_client/resources/topic.py
src/utils/goodreads_api_client/resources/update.py
src/utils/goodreads_api_client/resources/user.py
src/utils/goodreads_api_client/resources/user_shelf.py
src/utils/goodreads_api_client/resources/user_status.py
src/utils/goodreads_api_client/resources/work.py
src/utils/goodreads_api_client/tests/__init__.py
src/utils/goodreads_api_client/tests/conftest.py
src/utils/goodreads_api_client/tests/test_client.py
src/utils/goodreads_api_client/tests/test_transport.py
src/utils/goodreads_api_client/tests/resources/__init__.py
src/utils/goodreads_api_client/tests/resources/conftest.py
franklin_redfruitt-0.0.2.dist-info/LICENSE
franklin_redfruitt-0.0.2.dist-info/METADATA
franklin_redfruitt-0.0.2.dist-info/WHEEL
franklin_redfruitt-0.0.2.dist-info/top_level.txt
franklin_redfruitt-0.0.2.dist-info/RECORD
