Metadata-Version: 2.1
Name: franklin-redfruitt
Version: 0.0.2
Summary: Franklin Book Recommendations
Home-page: https://gitlab.com/redfruitt/Franklin
Author: redfruitt
Author-email: krishnaqmar@gmail.com
License: UNKNOWN
Platform: UNKNOWN
Classifier: Programming Language :: Python :: 3
Classifier: License :: OSI Approved :: MIT License
Classifier: Operating System :: OS Independent
Requires-Python: >=2.7
